message_send_local/__init__.py
message_send_local/campaign_message_send.py
message_send_local/constants.py
message_send_local-0.0.33.dist-info/METADATA
message_send_local-0.0.33.dist-info/WHEEL
message_send_local-0.0.33.dist-info/top_level.txt
message_send_local-0.0.33.dist-info/RECORD
