Metadata-Version: 2.4
Name: message-send-local
Version: 0.0.33
Summary: PyPI Package for Circles message_send_local Python
Home-page: https://github.com/circles-zone/message-send-local-local-python-package
Author: Circles
Author-email: info@circlez.ai
Classifier: Programming Language :: Python :: 3
Classifier: Operating System :: OS Independent
Requires-Dist: database-mysql-local>=0.1.10
Requires-Dist: criteria-local>=0.0.38
Requires-Dist: message-local>=0.0.123
Requires-Dist: messages-local>=0.0.49
Requires-Dist: logger-local>=0.0.175
Dynamic: author
Dynamic: author-email
Dynamic: classifier
Dynamic: description
Dynamic: description-content-type
Dynamic: home-page
Dynamic: requires-dist
Dynamic: summary
